<annotation><filename>6_bright_1.5.jpg</filename><size><width>448</width><height>448</height><depth>3</depth></size><object><name>coin_1</name><bndbox><xmin>115</xmin><ymin>111</ymin><xmax>135</xmax><ymax>131</ymax></bndbox></object><object><name>coin_2</name><bndbox><xmin>122</xmin><ymin>53</ymin><xmax>142</xmax><ymax>73</ymax></bndbox></object><object><name>coin_3</name><bndbox><xmin>351</xmin><ymin>108</ymin><xmax>371</xmax><ymax>128</ymax></bndbox></object><object><name>coin_4</name><bndbox><xmin>340</xmin><ymin>69</ymin><xmax>360</xmax><ymax>89</ymax></bndbox></object></annotation>